[{"question":"Co zabieramy ze sobą do szkoły?","answers":[{"text":"Plecak","points":40},{"text":"Książki","points":20},{"text":"Kanapki","points":20},{"text":"Zeszyty","points":10},{"text":"Piórnik","points":6},{"text":"Ściągi","points":4}]},{"question":"Podaj tytuły kultowych polskich komedii","answers":[{"text":"Sami Swoi","points":30},{"text":"Seksmisja","points":24},{"text":"Miś","points":20},{"text":"Chłopaki nie płaczą","points":10},{"text":"Killer","points":8},{"text":"Kogel Mogel","points":6}]},{"question":"Europejskie państwo większe od Polski","answers":[{"text":"Niemcy","points":31},{"text":"Francja","points":29},{"text":"Wielka Brytania","points":18},{"text":"Szwecja","points":12},{"text":"Hiszpania","points":10}]}]
